get_github_code/__init__.py
get_github_code/constants/__init__.py
get_github_code/constants/constants.py
get_github_code/decode/__init__.py
get_github_code/decode/decode.py
get_github_code/exceptions/__init__.py
get_github_code/exceptions/get_code_error.py
get_github_code/get_code/__init__.py
get_github_code/get_code/get_code.py
get_github_code/json/__init__.py
get_github_code/json/json.py
get_github_code/request/__init__.py
get_github_code/request/request.py
get_github_code-0.2.1.dist-info/LICENSE
get_github_code-0.2.1.dist-info/METADATA
get_github_code-0.2.1.dist-info/WHEEL
get_github_code-0.2.1.dist-info/RECORD
