Metadata-Version: 2.1
Name: get-github-code
Version: 0.2.1
Summary: a small python library to get code from github repositories.
Home-page: https://github.com/Vlad2030/get-code-from-github
License: GNU
Keywords: urllib3,aiohttp,asyncio,orjson
Author: vladdd0
Author-email: vlad123123v@gmail.com
Requires-Python: >=3.10.0,<4.0.0
Classifier: Development Status :: 2 - Pre-Alpha
Classifier: Environment :: Plugins
Classifier: Framework :: AsyncIO
Classifier: Intended Audience :: Developers
Classifier: License :: OSI Approved :: GNU Affero General Public License v3
Classifier: License :: Other/Proprietary License
Classifier: Operating System :: OS Independent
Classifier: Programming Language :: Python :: 3
Classifier: Programming Language :: Python :: 3.10
Classifier: Programming Language :: Python :: 3.11
Classifier: Programming Language :: Python :: 3
Classifier: Programming Language :: Python :: 3 :: Only
Classifier: Programming Language :: Python :: 3.10
Classifier: Programming Language :: Python :: 3.7
Classifier: Programming Language :: Python :: 3.8
Classifier: Programming Language :: Python :: 3.9
Classifier: Topic :: Software Development :: Libraries
Provides-Extra: all
Provides-Extra: orjson
Requires-Dist: aiohttp (>=3.8.3)
Requires-Dist: asyncio (>=3.4.3)
Requires-Dist: orjson (>=3.5.2) ; extra == "orjson" or extra == "all"
Requires-Dist: urllib3 (>=1.26.5)
Project-URL: Documentation, https://get-code-from-github.readthedocs.io/en/latest/
Project-URL: Repository, https://github.com/Vlad2030/get-code-from-github
